ref_resolver/__init__.py
ref_resolver/ref_resolver.py
ref_resolver-1.0.3.dist-info/DESCRIPTION.rst
ref_resolver-1.0.3.dist-info/METADATA
ref_resolver-1.0.3.dist-info/RECORD
ref_resolver-1.0.3.dist-info/WHEEL
ref_resolver-1.0.3.dist-info/metadata.json
ref_resolver-1.0.3.dist-info/top_level.txt
