Metadata-Version: 2.0
Name: ref-resolver
Version: 1.0.3
Summary: A lightweight python json schema ref resolver and inliner.
Home-page: https://github.com/purukaushik/ref-resolver
Author: Purush Swaminathan
Author-email: purukaushik@asu.edu
License: MPL 2.0
Download-URL: https://github.com/purukaushik/ref-resolver.git
Platform: UNKNOWN
Requires-Dist: jsonpath-rw
Requires-Dist: requests
Requires-Dist: simplejson
